autotst/__init__.py
autotst/autotst_types.py
autotst/functions.py
autotst/model.py
autotst/py.typed
autotst/splitted_sets.py
autotst/test.py
autotst-1.2.dist-info/LICENSE.md
autotst-1.2.dist-info/WHEEL
autotst-1.2.dist-info/METADATA
autotst-1.2.dist-info/RECORD
