Metadata-Version: 2.1
Name: autotst
Version: 1.2
Summary: Two-samples Testing and Distribution Shift Detection with AutoML
Home-page: https://jmkuebler.github.io/auto-tst/
Author: Jonas M. Kübler
Author-email: jonas.m.kuebler@tuebingen.mpg.de
Requires-Python: >=3.7.1,<3.10
Classifier: Programming Language :: Python :: 3
Classifier: Programming Language :: Python :: 3.8
Classifier: Programming Language :: Python :: 3.9
Requires-Dist: autogluon (>=0.4.2,<0.5.0)
Requires-Dist: importlib-metadata (>=1.4)
Requires-Dist: nptyping (>=1.4.4,<2.0.0)
Requires-Dist: numpy (>=1.21,<2.0)
Requires-Dist: pandas (>=1.3,<2.0)
Requires-Dist: pytest (>=7.1.2,<8.0.0)
Requires-Dist: torchvision (==0.11.3)
